setup.py
weather_history/__init__.py
weather_history/weather_history.py
weather_history.egg-info/PKG-INFO
weather_history.egg-info/SOURCES.txt
weather_history.egg-info/dependency_links.txt
weather_history.egg-info/top_level.txt